libmodbampy.abi3.so
modbampy/__init__.py
modbampy-0.10.0.dist-info/WHEEL
modbampy-0.10.0.dist-info/RECORD
modbampy-0.10.0.dist-info/top_level.txt
modbampy-0.10.0.dist-info/METADATA
modbampy-0.10.0.dist-info/entry_points.txt
modbampy.libs/libgssapi_krb5-497db0c6.so.2.2
modbampy.libs/libkrb5support-d0bcff84.so.0.1
modbampy.libs/libssl3-7d7debcb.so
modbampy.libs/libselinux-0922c95c.so.1
modbampy.libs/libk5crypto-b1f99d5c.so.3.1
modbampy.libs/libsasl2-84219a89.so.3.0.0
modbampy.libs/liblber-2-7eefa761.4.so.2.10.7
modbampy.libs/libnssutil3-5292dbaa.so
modbampy.libs/libplds4-f0f0f720.so
modbampy.libs/libidn-97d26f25.so.11.6.11
modbampy.libs/libcrypto-d3570994.so.1.0.2k
modbampy.libs/libpcre-9513aab5.so.1.2.0
modbampy.libs/libplc4-4e123408.so
modbampy.libs/libssl-cd1d6220.so.1.0.2k
modbampy.libs/libnss3-4d0ee2f8.so
modbampy.libs/libkrb5-fcafa220.so.3.3
modbampy.libs/libsmime3-985a6d0a.so
modbampy.libs/liblzma-004595ca.so.5.2.2
modbampy.libs/libnspr4-4f93563e.so
modbampy.libs/libcom_err-2abe824b.so.2.1
modbampy.libs/libbz2-a273e504.so.1.0.6
modbampy.libs/libkeyutils-dfe70bd6.so.1.5
modbampy.libs/libssh2-1408df5a.so.1.0.1
modbampy.libs/libcrypt-8f974802.so.1
modbampy.libs/libcurl-602541fb.so.4.3.0
modbampy.libs/libldap-2-b8523ca2.4.so.2.10.7
modbampy.libs/libdeflate-f43950dc.so.0
