Metadata-Version: 2.1
Name: modbampy
Version: 0.10.0
Summary: Accessing modified-base data from BAM files.
Home-page: https://github.com/epi2me-labs/modbam2bed
Author: cwright
Author-email: cwright@nanoporetech.com
License-File: LICENSE
Requires-Dist: cffi (==1.15.0)
Requires-Dist: numpy
